setup.py
Recess_Distribution/Binomial_class.py
Recess_Distribution/Distribution_class.py
Recess_Distribution/Gaussian_class.py
Recess_Distribution/__init__.py
Recess_Distribution.egg-info/PKG-INFO
Recess_Distribution.egg-info/SOURCES.txt
Recess_Distribution.egg-info/dependency_links.txt
Recess_Distribution.egg-info/not-zip-safe
Recess_Distribution.egg-info/top_level.txt