Metadata-Version: 1.0
Name: Recess-Distribution
Version: 1.3
Summary: Gaussian distributions and Binomial distribution
Home-page: UNKNOWN
Author: Rania Hamada
Author-email: raniahamada10@hotmail.com
License: UNKNOWN
Platform: UNKNOWN
